Metadata-Version: 2.1
Name: dikson
Version: 0.2
Summary: Modulo para exemplificar construcao de projetos Python no curso PyTools
Home-page: https://github.com/DiksonSantos/LibPythonPRO
Author: dikson
Author-email: dikson_santos@outlook.com
License: GNU AFFERO GENERAL PUBLIC LICENSE
Platform: UNKNOWN
Classifier: Programming Language :: Python :: 3
